smdebug/__init__.py
smdebug/_version.py
smdebug/exceptions.py
smdebug/analysis/__init__.py
smdebug/analysis/utils.py
smdebug/core/__init__.py
smdebug/core/collection.py
smdebug/core/collection_manager.py
smdebug/core/config_constants.py
smdebug/core/config_validator.py
smdebug/core/error_handling_agent.py
smdebug/core/hook.py
smdebug/core/hook_utils.py
smdebug/core/index_reader.py
smdebug/core/json_config.py
smdebug/core/locations.py
smdebug/core/logger.py
smdebug/core/modes.py
smdebug/core/reader.py
smdebug/core/reduction_config.py
smdebug/core/reductions.py
smdebug/core/s3_utils.py
smdebug/core/sagemaker_utils.py
smdebug/core/save_config.py
smdebug/core/singleton_utils.py
smdebug/core/state_store.py
smdebug/core/tensor.py
smdebug/core/utils.py
smdebug/core/writer.py
smdebug/core/access_layer/__init__.py
smdebug/core/access_layer/base.py
smdebug/core/access_layer/file.py
smdebug/core/access_layer/s3.py
smdebug/core/access_layer/s3handler.py
smdebug/core/access_layer/utils.py
smdebug/core/tfevent/__init__.py
smdebug/core/tfevent/event_file_reader.py
smdebug/core/tfevent/event_file_writer.py
smdebug/core/tfevent/events_writer.py
smdebug/core/tfevent/index_file_writer.py
smdebug/core/tfevent/summary.py
smdebug/core/tfevent/timeline_file_writer.py
smdebug/core/tfevent/util.py
smdebug/core/tfevent/proto/__init__.py
smdebug/core/tfevent/proto/attr_value_pb2.py
smdebug/core/tfevent/proto/event_pb2.py
smdebug/core/tfevent/proto/graph_pb2.py
smdebug/core/tfevent/proto/node_def_pb2.py
smdebug/core/tfevent/proto/resource_handle_pb2.py
smdebug/core/tfevent/proto/summary_pb2.py
smdebug/core/tfevent/proto/tensor_pb2.py
smdebug/core/tfevent/proto/tensor_shape_pb2.py
smdebug/core/tfevent/proto/types_pb2.py
smdebug/core/tfevent/proto/versions_pb2.py
smdebug/core/tfrecord/__init__.py
smdebug/core/tfrecord/_crc32c.py
smdebug/core/tfrecord/record_reader.py
smdebug/core/tfrecord/record_writer.py
smdebug/core/tfrecord/tensor_reader.py
smdebug/mxnet/__init__.py
smdebug-1.0.34.dist-info/LICENSE
smdebug-1.0.34.dist-info/LICENSE-THIRD-PARTY
smdebug-1.0.34.dist-info/METADATA
smdebug-1.0.34.dist-info/NOTICE
smdebug-1.0.34.dist-info/WHEEL
smdebug-1.0.34.dist-info/top_level.txt
smdebug-1.0.34.dist-info/RECORD
