Metadata-Version: 2.1
Name: smdebug
Version: 1.0.34
Summary: Amazon SageMaker Debugger is an offering from AWS which helps you automate the debugging of machine learning training jobs.
Home-page: https://github.com/awslabs/sagemaker-debugger
Author: AWS DeepLearning Team
License: Apache License Version 2.0
Platform: UNKNOWN
Classifier: Programming Language :: Python :: 3
Classifier: Programming Language :: Python :: 3.6
Classifier: Programming Language :: Python :: 3.7
Classifier: Programming Language :: Python :: 3.8
Classifier: Programming Language :: Python :: 3 :: Only
Classifier: License :: OSI Approved :: Apache Software License
Classifier: Operating System :: OS Independent
Requires-Python: >=3.6
License-File: LICENSE-THIRD-PARTY
License-File: LICENSE
License-File: NOTICE
Requires-Dist: protobuf (<=3.20.3,>=3.20.0)
Requires-Dist: numpy (>=1.16.0)
Requires-Dist: packaging
Requires-Dist: boto3 (>=1.10.32)
Requires-Dist: pyinstrument (==3.4.2)
